unicboard_billing_sdk/__init__.py
unicboard_billing_sdk/billing_api_sdk.py
unicboard_billing_sdk/constants.py
unicboard_billing_sdk/response_models.py
unicboard_billing_sdk/utils.py
unicboard_billing_sdk-2.2.1.dist-info/LICENSE
unicboard_billing_sdk-2.2.1.dist-info/METADATA
unicboard_billing_sdk-2.2.1.dist-info/WHEEL
unicboard_billing_sdk-2.2.1.dist-info/top_level.txt
unicboard_billing_sdk-2.2.1.dist-info/RECORD
