Metadata-Version: 2.1
Name: unicboard-billing-sdk
Version: 2.2.1
Summary: Unicboard billing api
Home-page: https://github.com/uniclab-01/billing-api
Author: Unic-lab
Author-email: a.brilon@unic-lab.by
License: MIT
Platform: any
Classifier: Intended Audience :: Developers
Classifier: License :: OSI Approved :: MIT License
Classifier: Programming Language :: Python
Classifier: Programming Language :: Python :: 3.6
Classifier: Programming Language :: Python :: 3.7
Classifier: Programming Language :: Python :: 3.8
Classifier: Programming Language :: Python :: 3.9
Classifier: Operating System :: OS Independent
License-File: LICENSE
Requires-Dist: requests (>=2.26.0)
